dokang/__init__.py
dokang/api.py
dokang/app.py
dokang/cli.py
dokang/compat.py
dokang/utils.py
dokang/views.py
dokang/backends/__init__.py
dokang/backends/whoosh.py
dokang/harvesters/__init__.py
dokang/harvesters/base.py
dokang/harvesters/html.py
dokang/harvesters/sphinx.py
dokang/static/css/style.css
dokang/static/img/favicon.ico
dokang/templates/layout.pt
dokang/templates/search.pt
tests/__init__.py
tests/test_harvester.py
tests/test_web.py
tests/test_whoosh.py
Dokang-0.10.1.dist-info/LICENSE.txt
Dokang-0.10.1.dist-info/METADATA
Dokang-0.10.1.dist-info/WHEEL
Dokang-0.10.1.dist-info/entry_points.txt
Dokang-0.10.1.dist-info/top_level.txt
Dokang-0.10.1.dist-info/RECORD
