Metadata-Version: 2.1
Name: Dokang
Version: 0.10.1
Summary: Lightweight web documentation repository with a search engine
Home-page: https://dokang.readthedocs.io/
Author: Polyconseil
Author-email: opensource+dokang@polyconseil.fr
Keywords: documentation repository search engine
Classifier: Development Status :: 4 - Beta
Classifier: Environment :: Console
Classifier: License :: OSI Approved :: BSD License
Classifier: Programming Language :: Python
Classifier: Programming Language :: Python :: 3.7
Classifier: Programming Language :: Python :: 3.8
Classifier: Framework :: Pyramid
Classifier: Topic :: Internet :: WWW/HTTP
Classifier: Topic :: Internet :: WWW/HTTP :: WSGI :: Application
Classifier: Topic :: Text Processing :: Markup :: HTML
License-File: LICENSE.txt
Requires-Dist: beautifulsoup4 (==4.11.2)
Requires-Dist: Chameleon (==3.10.2)
Requires-Dist: pyramid (==1.10.8)
Requires-Dist: pyramid-chameleon (==0.3)
Requires-Dist: Whoosh (==2.7.4)
Requires-Dist: WTForms (==3.0.1)
